gempa_terkini/__init__.py
Earthquake_Indonesia-0.5.dist-info/METADATA
Earthquake_Indonesia-0.5.dist-info/WHEEL
Earthquake_Indonesia-0.5.dist-info/top_level.txt
Earthquake_Indonesia-0.5.dist-info/RECORD
