Metadata-Version: 2.1
Name: Earthquake-Indonesia
Version: 0.5
Summary: This Package will get the latest eartquake from BMKG |Meteorogical, Climatological, and Geophysical agency
Home-page: https://github.com/Ahmadfauzan1922/Earthquake-Indonesia
Author: Ahmad Fauzan Z
Author-email: ahmadfauzanzain10@gmail.com
License: UNKNOWN
Platform: UNKNOWN
Classifier: Programming Language :: Python :: 3
Classifier: License :: OSI Approved :: MIT License
Classifier: Operating System :: OS Independent
Classifier: Development Status :: 5 - Production/Stable
Requires-Python: >=3.6
